aquacropgym/__init__.py
aquacropgym/agents.py
aquacropgym/envs.py
aquacropgym/utils.py
aquacropgym-1.0.0.dist-info/METADATA
aquacropgym-1.0.0.dist-info/WHEEL
aquacropgym-1.0.0.dist-info/top_level.txt
aquacropgym-1.0.0.dist-info/RECORD
