Metadata-Version: 2.1
Name: aquacropgym
Version: 1.0.0
Summary: openai-gym crop simulation environment
Home-page: https://github.com/aquacropos/aquacrop-gym
Author: Thomas Kelly
Author-email: thomas.kelly-2@manchester.ac.uk
Project-URL: Bug Tracker, https://github.com/aquacropos/aquacrop-gym/issues
Keywords: aquacrop-gym aquacrop,aquacropos,aquacrop-ospy,python
Classifier: Programming Language :: Python :: 3.8
Classifier: Programming Language :: Python :: 3.9
Classifier: Programming Language :: Python :: 3.10
Classifier: License :: OSI Approved :: MIT License
Classifier: Operating System :: MacOS
Classifier: Operating System :: Microsoft
Classifier: Operating System :: POSIX :: Linux
Classifier: Natural Language :: English
Requires-Python: >=3.6
Requires-Dist: aquacrop (==1.1.2)
Requires-Dist: aquacropeto (==0.1.1)
Requires-Dist: gym (==0.19.0)
Requires-Dist: numpy (==1.21.2)
Requires-Dist: pandas (==1.4.0)
Requires-Dist: lz4
Requires-Dist: torch (==1.11.0)
Requires-Dist: dm-tree
Requires-Dist: ray[rllib]
Requires-Dist: tensorflow (==2.8.0)
Requires-Dist: protobuf (==3.20.0)
